testform/__init__.py
testform/geckodriver.exe
testform/testform.py
testform_888-1.0.dist-info/METADATA
testform_888-1.0.dist-info/RECORD
testform_888-1.0.dist-info/WHEEL
testform_888-1.0.dist-info/top_level.txt
