Metadata-Version: 2.1
Name: testform-888
Version: 1.0
Summary: person
Home-page: UNKNOWN
Author: yuan
Author-email: 3089328436@qq.com
Maintainer: yuan
Maintainer-email: 3089328436@qq.com
License: BSD License
Platform: all
Requires-Dist: selenium (>=3.11.0)
